src/__init__.py
src/logins.py
passwallet-1.0.dist-info/LICENSE
passwallet-1.0.dist-info/METADATA
passwallet-1.0.dist-info/WHEEL
passwallet-1.0.dist-info/top_level.txt
passwallet-1.0.dist-info/RECORD
