Metadata-Version: 2.1
Name: passwallet
Version: 1.0
Summary: Password Wallet
Home-page: https://github.com/Nimit-Khurana/pyWallet
Author: Richie
Author-email: nimitkhuranaa@gmail.com
License: UNKNOWN
Platform: UNKNOWN
